correct_horse-0.1.2.dist-info/DESCRIPTION.rst
correct_horse-0.1.2.dist-info/METADATA
correct_horse-0.1.2.dist-info/RECORD
correct_horse-0.1.2.dist-info/WHEEL
correct_horse-0.1.2.dist-info/entry_points.txt
correct_horse-0.1.2.dist-info/metadata.json
correct_horse-0.1.2.dist-info/top_level.txt
correcthorse/__init__.py
