Metadata-Version: 2.0
Name: correct-horse
Version: 0.1.2
Summary: Print strong, memorable passphrases
Home-page: https://github.com/bbiw/correct-horse
Author: Terrel Shumway
Author-email: algae-ester-1925-riga-seth@shumway.us
License: MIT
Platform: UNKNOWN
Classifier: Environment :: Console
Classifier: Development Status :: 3 - Alpha
Classifier: Intended Audience :: End Users/Desktop
Classifier: License :: OSI Approved :: MIT License
Classifier: Natural Language :: English
Classifier: Programming Language :: Python :: 3
Classifier: Programming Language :: Python :: 3.3
Classifier: Programming Language :: Python :: 3.4
Classifier: Programming Language :: Python :: 3.5
Classifier: Programming Language :: Python :: 3.6
Classifier: Programming Language :: Python :: 3 :: Only
Classifier: Topic :: Security
Requires-Dist: Click
